<?xml version="1.0" encoding="utf-8"?><items termsofuse="https://boardgamegeek.com/xmlapi/termsofuse"><item type="boardgameexpansion" id="165122">
         <thumbnail>https://cf.geekdo-images.com/thumb/img/pG1Co0HO7hObhtI3VLGUu8S-gKk=/fit-in/200x150/pic2273477.jpg</thumbnail>
      <image>https://cf.geekdo-images.com/original/img/j_kKDiiFVLmpeorvTErLxVW9dz8=/0x0/pic2273477.jpg</image>
                                     				
				<name type="primary" sortindex="1" value="Whitewater: Jutting Jetties" />
			
						                           
						               													<description>This official Mayfair promo expansion is included on a tile sheet titled: Limited Edition Promo Expansion Set #10, which can be found in issue #175 of GTM.&amp;#10;&amp;#10;Includes two River Hex tiles.&amp;#10;&amp;#10;SETUP:&amp;#10;You may place either or both of the 3-hex tiles anywhere on your river boards as long as two of the three hexes line up with river hexes underneath.&amp;#10;&amp;#10;Treat these tile river features as you would any on the standard the board tiles [i](sic)[/i]. These tiles do not move during gameplay.&amp;#10;&amp;#10;</description>
										      	               				<yearpublished value="2014" />
						               				<minplayers value="0" />
						               				<maxplayers value="0" />
						      			<poll name="suggested_numplayers" title="User Suggested Number of Players" totalvotes="0">
			
		<results numplayers="0+">		
				</results>					
	</poll> 			               				<playingtime value="0" />
						               				<minplaytime value="0" />
						               				<maxplaytime value="0" />
						               				<minage value="0" />
						      			<poll name="suggested_playerage" title="User Suggested Player Age" totalvotes="0">
	</poll> 			      			<poll name="language_dependence" title="Language Dependence" totalvotes="0">
	</poll> 			      			 			      				
		 			

			
		
					<link type="boardgamecategory" id="1042" value="Expansion for Base-game" />
		
									
				
		 			

			
		
					<link type="boardgamecategory" id="1031" value="Racing" />
		
									
			

			      				
		 			

			
		
					<link type="boardgamemechanic" id="2001" value="Action Point Allowance System" />
		
									
				
		 			

			
		
					<link type="boardgamemechanic" id="2014" value="Betting/Wagering" />
		
									
				
		 			

			
		
					<link type="boardgamemechanic" id="2072" value="Dice Rolling" />
		
									
				
		 			

			
		
					<link type="boardgamemechanic" id="2019" value="Partnerships" />
		
									
			

			      			

			      			

			      				
		 			

			
		
					<link type="boardgameexpansion" id="93563" value="Whitewater" inbound="true"/>
		
									
			

			      			

			      			

			      				
		 			

			
		
					<link type="boardgamecompilation" id="165115" value="Mayfair Games' Limited Edition Promo Expansion Set #10" />
		
									
			

			      			

			      			

			      	      	      				
		 			

			
		
					<link type="boardgamedesigner" id="1379" value="Fréderic Moyersoen" />
		
									
			

			      			

			      	      				
		 			

			
		
					<link type="boardgamepublisher" id="10" value="Mayfair Games" />
		
									
			

			
	

	

	
	
	
   		<statistics page="1">
								<ratings >
			<usersrated value="2" />
			<average value="6.5" />
			<bayesaverage value="0" />

			<ranks>
															<rank type="subtype" id="1" name="boardgame" friendlyname="Board Game Rank" value="Not Ranked" bayesaverage="Not Ranked" />
												</ranks>

			<stddev value="0.5" />
			<median value="0" />
			<owned value="35" />
			<trading value="14" />
			<wanting value="3" />
			<wishing value="5" />
			<numcomments value="4" />
			<numweights value="0" />
			<averageweight value="0" />
			</ratings>
								</statistics>
     
	
          
</item>
</items>