<?xml version="1.0" encoding="utf-8"?><items termsofuse="https://boardgamegeek.com/xmlapi/termsofuse"><item type="videogame" id="165430">
                                     				
				<name type="primary" sortindex="1" value="Moonrise" />
			
						                           
						               													<description>User Summary&amp;#10;&amp;#10;The basic premise of Moonrise is to raise and use creatures, known as Solari, to battle with other Wardens. Some Solari have been corrupted and turned into rampaging Lunari, and you must cleanse and then employ them in battle. Unlike Pokemon, Moonrise makes use of many character personalization options.&amp;#10;&amp;#10;</description>
										      				
		 			

			
		
					<link type="videogameplatform" id="4443" value="iPhone" />
		
									
			

			      				
		 			

			
		
					<link type="videogamegenre" id="2155" value="RPG" />
		
									
			

			      				
		 			

			
		
					<link type="videogametheme" id="2148" value="Fantasy" />
		
									
			

			      			

			      			

			      				
		 			

			
		
					<link type="videogamemode" id="2149" value="Single-Player" />
		
									
			

			               				<minplayers value="1" />
						               				<maxplayers value="1" />
						               				<releasedate value="2015-02-24" />
						      				
		 			

			
		
					<link type="videogamedeveloper" id="25001" value="Undead Labs" />
		
									
			

			      				
		 			

			
		
					<link type="videogamepublisher" id="17221" value="Kabam" />
		
									
			

			      			

			      			

			      			

			      			

			
	

	

	
	
	
   		<statistics page="1">
								<ratings >
			<usersrated value="0" />
			<average value="0" />
			<bayesaverage value="0" />

			<ranks>
															<rank type="subtype" id="32" name="videogame" friendlyname="Video Game Rank" value="Not Ranked" bayesaverage="Not Ranked" />
																				<rank type="family" id="4443" name="iphone" friendlyname="iPhone Rank" value="Not Ranked" bayesaverage="Not Ranked" />
												</ranks>

			<stddev value="0" />
			<median value="0" />
			<owned value="0" />
			<trading value="0" />
			<wanting value="0" />
			<wishing value="0" />
			<numcomments value="0" />
			<numweights value="0" />
			<averageweight value="0" />
			</ratings>
								</statistics>
     
	
          
</item>
</items>