<?xml version="1.0" encoding="utf-8"?><items termsofuse="https://boardgamegeek.com/xmlapi/termsofuse"><item type="rpgitem" id="166411">
         <thumbnail>https://cf.geekdo-images.com/thumb/img/LEs8LIjJHyj614NyDbRYBwwP7P4=/fit-in/200x150/pic2249021.jpg</thumbnail>
      <image>https://cf.geekdo-images.com/original/img/0WDwsfqzOVQ156G71A58P1XuW8M=/0x0/pic2249021.jpg</image>
                                     				
				<name type="primary" sortindex="3" value="A Day At The Races" />
			
						                           
						      				
		 			

			
		
					<link type="rpg" id="11105" value="Dungeon World" />
		
									
			

			               													<description>From publisher blurb:&amp;#10;&amp;#10;On Your Marks!&amp;#10;&amp;#10;Welcome to the races... Grab your mount or hop into your vehicle! Do you have what it takes to win? Can you snatch victory from the jaws of defeat? Perhaps most importantly, will you live up to the expectations of your adoring fans?&amp;#10;&amp;#10;Take the Lead! Gain new fans! Earn more Coin, either through prize money or through effective betting!&amp;#10;&amp;#10;A Day At The Races covers a new Dungeon World move for racing as well as 6 sub-moves and a few rules on how to handle betting on races.&amp;#10;&amp;#10;</description>
										               				<yearpublished value="2014" />
						      				
		 			

			
		
					<link type="rpggenre" id="155" value="Fantasy (High Fantasy)" />
		
									
			

			      				
		 			

			
		
					<link type="rpgsetting" id="44483" value="Wor" />
		
									
			

			      			

			               				<seriescode value="" />
						      				
		 			

			
		
					<link type="rpgcategory" id="2108" value="Sourcebook (rules/options to enhance play)" />
		
									
			

			      				
		 			

			
		
					<link type="rpgmechanic" id="2121" value="Action Table (table determines action outcomes)" />
		
									
				
		 			

			
		
					<link type="rpgmechanic" id="2101" value="Attribute/Stat Based (STR, CON, PER, etc)" />
		
									
				
		 			

			
		
					<link type="rpgmechanic" id="2095" value="Class Based (Pilot, Wizard, Scientist, etc)" />
		
									
				
		 			

			
		
					<link type="rpgmechanic" id="2099" value="Description Based (Narrative more so than Dice)" />
		
									
				
		 			

			
		
					<link type="rpgmechanic" id="2112" value="Dice (Primarily d6)" />
		
									
				
		 			

			
		
					<link type="rpgmechanic" id="2122" value="Dice (Various)" />
		
									
				
		 			

			
		
					<link type="rpgmechanic" id="2096" value="Level Based (Earn XP and level up)" />
		
									
				
		 			

			
		
					<link type="rpgmechanic" id="2133" value="Race Based (Player Race/Species affects gameplay)" />
		
									
			

			      				
		 			

			
		
					<link type="rpgpublisher" id="4602" value="Three Sages Games" />
		
									
			

			      				
		 			

			
		
					<link type="rpgdesigner" id="39867" value="Curtis Lyon" />
		
									
			

			      				
		 			

			
		
					<link type="rpgartist" id="31577" value="Shaman's Stockart" />
		
									
			

			      				
		 			

			
		
					<link type="rpgproducer" id="39867" value="Curtis Lyon" />
		
									
				
		 			

			
		
					<link type="rpgproducer" id="39868" value="Sarah Lyon" />
		
									
			

			
	

	

	
	
	
   		<statistics page="1">
								<ratings >
			<usersrated value="0" />
			<average value="0" />
			<bayesaverage value="0" />

			<ranks>
															<rank type="subtype" id="16" name="rpgitem" friendlyname="RPG Item Rank" value="Not Ranked" bayesaverage="Not Ranked" />
												</ranks>

			<stddev value="0" />
			<median value="0" />
			<owned value="0" />
			<trading value="0" />
			<wanting value="0" />
			<wishing value="0" />
			<numcomments value="0" />
			<numweights value="0" />
			<averageweight value="0" />
			</ratings>
								</statistics>
     
	
          
</item>
</items>