<?xml version="1.0" encoding="utf-8"?><items termsofuse="https://boardgamegeek.com/xmlapi/termsofuse"><item type="rpgitem" id="166687">
         <thumbnail>https://cf.geekdo-images.com/thumb/img/UkjTEk4Au3J1xXLVNOhcci0QWNw=/fit-in/200x150/pic2255898.jpg</thumbnail>
      <image>https://cf.geekdo-images.com/original/img/D-v_VMOTKRUvi4a_F2E5CrTILsE=/0x0/pic2255898.jpg</image>
                                     				
				<name type="primary" sortindex="1" value="Terrors of the Ancient World" />
			
						                           
						      				
		 			

			
		
					<link type="rpg" id="11105" value="Dungeon World" />
		
									
			

			               													<description>From publisher blurb:&amp;#10;&amp;#10;Terrors of the Ancient World is a collection of monsters to liven up your Dungeon World game. Inside this book you will find over a dozen new monsters, all of them illustrated in glorious full colour.&amp;#10;&amp;#10;Each monster comes with some combination of adventure hooks, custom moves, traps, fronts and dangers, magical items, and even a couple of maps. Demons can be summoned and bargained with, gods can be worshipped in exchange for new spells and other special powers.&amp;#10;&amp;#10;There is also a new base class, the Satyr, along with satyr race option moves for other classes.&amp;#10;&amp;#10;</description>
										               				<yearpublished value="2014" />
						      				
		 			

			
		
					<link type="rpggenre" id="155" value="Fantasy (High Fantasy)" />
		
									
			

			      			

			      				
		 			

			
		
					<link type="rpgseries" id="25930" value="Monthly Monsters" />
		
									
			

			               				<seriescode value="MM1" />
						      				
		 			

			
		
					<link type="rpgcategory" id="2108" value="Sourcebook (rules/options to enhance play)" />
		
									
			

			      				
		 			

			
		
					<link type="rpgmechanic" id="2121" value="Action Table (table determines action outcomes)" />
		
									
				
		 			

			
		
					<link type="rpgmechanic" id="2101" value="Attribute/Stat Based (STR, CON, PER, etc)" />
		
									
				
		 			

			
		
					<link type="rpgmechanic" id="2095" value="Class Based (Pilot, Wizard, Scientist, etc)" />
		
									
				
		 			

			
		
					<link type="rpgmechanic" id="2099" value="Description Based (Narrative more so than Dice)" />
		
									
				
		 			

			
		
					<link type="rpgmechanic" id="2112" value="Dice (Primarily d6)" />
		
									
				
		 			

			
		
					<link type="rpgmechanic" id="2122" value="Dice (Various)" />
		
									
				
		 			

			
		
					<link type="rpgmechanic" id="2096" value="Level Based (Earn XP and level up)" />
		
									
				
		 			

			
		
					<link type="rpgmechanic" id="2133" value="Race Based (Player Race/Species affects gameplay)" />
		
									
			

			      				
		 			

			
		
					<link type="rpgpublisher" id="28236" value="Red Box Vancouver" />
		
									
			

			      				
		 			

			
		
					<link type="rpgdesigner" id="19782" value="Johnstone Metzger" />
		
									
			

			      				
		 			

			
		
					<link type="rpgartist" id="78226" value="Nathan Jones" />
		
									
			

			      				
		 			

			
		
					<link type="rpgproducer" id="19782" value="Johnstone Metzger" />
		
									
			

			
	

	

	
	
	
   		<statistics page="1">
								<ratings >
			<usersrated value="2" />
			<average value="7.5" />
			<bayesaverage value="0" />

			<ranks>
															<rank type="subtype" id="16" name="rpgitem" friendlyname="RPG Item Rank" value="Not Ranked" bayesaverage="Not Ranked" />
												</ranks>

			<stddev value="0.5" />
			<median value="0" />
			<owned value="17" />
			<trading value="0" />
			<wanting value="0" />
			<wishing value="0" />
			<numcomments value="0" />
			<numweights value="0" />
			<averageweight value="0" />
			</ratings>
								</statistics>
     
	
          
</item>
</items>