<?xml version="1.0" encoding="utf-8"?><items termsofuse="https://boardgamegeek.com/xmlapi/termsofuse"><item type="rpgitem" id="166951">
         <thumbnail>https://cf.geekdo-images.com/thumb/img/vKiK28fh7cpXVCAIYOZmS9eMlgk=/fit-in/200x150/pic2258044.png</thumbnail>
      <image>https://cf.geekdo-images.com/original/img/Zz5XIRutt4iQktOzK_4k5Dtj80o=/0x0/pic2258044.png</image>
                                     				
				<name type="primary" sortindex="1" value="Blood Opera" />
			
						                           
						      				
		 			

			
		
					<link type="rpg" id="4279" value="Fiasco" />
		
									
			

			               													<description>From publisher blurb:&amp;#10;&amp;#10;The nail that sticks out gets hammered down&amp;#10;&amp;#10;Duty, honor, structure. It binds us all together towards our divine purpose and keeps order, but it rules a man from birth until death, and it favors some while demanding from others.&amp;#10;&amp;#10;If the rules could be bent for just this one time, if the gods could shift their affections only slightly, we could fid some small measure more than fate has set aside for us.&amp;#10;&amp;#10;That is, of course, if everyone else stays in their place afterward...&amp;#10;&amp;#10;</description>
										               				<yearpublished value="2012" />
						      				
		 			

			
		
					<link type="rpggenre" id="278" value="Culture (Asian / Far Eastern)" />
		
									
				
		 			

			
		
					<link type="rpggenre" id="184" value="History" />
		
									
			

			      			

			      			

			               				<seriescode value="" />
						      				
		 			

			
		
					<link type="rpgcategory" id="2084" value="Scenario / Adventure / Module" />
		
									
			

			      				
		 			

			
		
					<link type="rpgmechanic" id="2099" value="Description Based (Narrative more so than Dice)" />
		
									
				
		 			

			
		
					<link type="rpgmechanic" id="2112" value="Dice (Primarily d6)" />
		
									
				
		 			

			
		
					<link type="rpgmechanic" id="2089" value="GM-less (No gamemaster needed to play)" />
		
									
			

			      				
		 			

			
		
					<link type="rpgpublisher" id="1001" value="(Web published)" />
		
									
			

			      				
		 			

			
		
					<link type="rpgdesigner" id="78283" value="Arnold Cassell" />
		
									
			

			      				
		 			

			
		
					<link type="rpgartist" id="78283" value="Arnold Cassell" />
		
									
			

			      				
		 			

			
		
					<link type="rpgproducer" id="78283" value="Arnold Cassell" />
		
									
			

			
	

	

	
	
	
   		<statistics page="1">
								<ratings >
			<usersrated value="0" />
			<average value="0" />
			<bayesaverage value="0" />

			<ranks>
															<rank type="subtype" id="16" name="rpgitem" friendlyname="RPG Item Rank" value="Not Ranked" bayesaverage="Not Ranked" />
												</ranks>

			<stddev value="0" />
			<median value="0" />
			<owned value="3" />
			<trading value="0" />
			<wanting value="0" />
			<wishing value="1" />
			<numcomments value="0" />
			<numweights value="0" />
			<averageweight value="0" />
			</ratings>
								</statistics>
     
	
          
</item>
</items>