<?xml version="1.0" encoding="utf-8"?><items termsofuse="https://boardgamegeek.com/xmlapi/termsofuse"><item type="rpgissue" id="167324">
         <thumbnail>https://cf.geekdo-images.com/thumb/img/ylJwuz9X17TUGkEfDmh97JToDHk=/fit-in/200x150/pic2263211.png</thumbnail>
      <image>https://cf.geekdo-images.com/original/img/S2GhPGUQFkwi9RTHdsxSnCj9pcw=/0x0/pic2263211.png</image>
                                     				
				<name type="primary" sortindex="1" value="Playground Magazine (Issue 6 – 2012)" />
			
						                           
						               				<datepublished value="2012-09-00" />
						               				<issueindex value="6" />
						      				
		 			

			
		
					<link type="rpgissue" id="10043" value="Playground Magazine" inbound="true"/>
		
									
			

			      				
		 			

			
		
					<link type="rpgdesigner" id="59397" value="Kasper Friis Hansen" />
		
									
				
		 			

			
		
					<link type="rpgdesigner" id="60063" value="Rasmus Høgdall" />
		
									
				
		 			

			
		
					<link type="rpgdesigner" id="60059" value="Bjarke Pedersen" />
		
									
				
		 			

			
		
					<link type="rpgdesigner" id="53396" value="Evan Torner" />
		
									
				
		 			

			
		
					<link type="rpgdesigner" id="18664" value="Aaron Vanek" />
		
									
			

			      				
		 			

			
		
					<link type="rpgartist" id="34951" value="Lars Nøhr Andresen" />
		
									
				
		 			

			
		
					<link type="rpgartist" id="41965" value="Peter Munthe-Kaas" />
		
									
			

			      				
		 			

			
		
					<link type="rpgproducer" id="59397" value="Kasper Friis Hansen" />
		
									
				
		 			

			
		
					<link type="rpgproducer" id="41950" value="Claus Raasted" />
		
									
			

			      				
		 			

			
		
					<link type="rpgpublisher" id="4" value="(Self-Published)" />
		
									
				
		 			

			
		
					<link type="rpgpublisher" id="1001" value="(Web published)" />
		
									
			

			               													<description>&amp;quot;From the introduction:'&amp;#10;&amp;#10;In case you were wondering whether or not we are artists, stop wondering. We are. Artists are also the worst breed of people at talking trash about fantastic projects... It doesn't have the same impact the second time you see a urinal in an art gallery, but let us give a bit of elbow room to theose who have not seen the urinal there before.&amp;#10;&amp;#10;Highlights&amp;#10;Fastival of Change:&amp;#10;We're laughing at YOU!&amp;#10;States of Stasis: review - Solmukohta 2012&amp;#10;Krigslive - a changing LARP: They fight, and fight, and fight and fight.&amp;#10;24-hour LARP design: Aaron Vanek on fast design&amp;#10;5 things we lie about in LARP&amp;#10;The Nordic Invasion: What Nordic &amp;amp; American LARPers can learn from each other&amp;#10;A strange journey into Solmukohta: What is it and what isn't it?&amp;#10;How bleed is ruining LARP: personal uproar from Rasmus H&amp;oslash;gdall&amp;#10;&amp;#10;</description>
										      			

			
	

	

	
	
	
   		<statistics page="1">
								<ratings >
			<usersrated value="0" />
			<average value="0" />
			<bayesaverage value="0" />

			<ranks>
															<rank type="subtype" id="49" name="rpgissue" friendlyname="RPG Issue Rank" value="Not Ranked" bayesaverage="Not Ranked" />
												</ranks>

			<stddev value="0" />
			<median value="0" />
			<owned value="1" />
			<trading value="0" />
			<wanting value="0" />
			<wishing value="0" />
			<numcomments value="0" />
			<numweights value="0" />
			<averageweight value="0" />
			</ratings>
								</statistics>
     
	
          
</item>
</items>