<?xml version="1.0" encoding="utf-8"?><items termsofuse="https://boardgamegeek.com/xmlapi/termsofuse"><item type="videogame" id="167908">
                                     				
				<name type="primary" sortindex="1" value="Star Nomad" />
			
						                           
						               													<description>User Summary&amp;#10;&amp;#10;Star Nomad is a top-down 2D RPG/RTS sandbox spacesim. You can choose between 6 different kinds of characters to play. It has multiple ship classes to fly, and all ships are up-gradable with modules.&amp;#10;&amp;#10;</description>
										      				
		 			

			
		
					<link type="videogameplatform" id="6063" value="Android" />
		
									
				
		 			

			
		
					<link type="videogameplatform" id="6826" value="iPad" />
		
									
				
		 			

			
		
					<link type="videogameplatform" id="4729" value="Macintosh" />
		
									
				
		 			

			
		
					<link type="videogameplatform" id="4977" value="Windows" />
		
									
			

			      				
		 			

			
		
					<link type="videogamegenre" id="2166" value="Real Time Strategy" />
		
									
				
		 			

			
		
					<link type="videogamegenre" id="2155" value="RPG" />
		
									
			

			      				
		 			

			
		
					<link type="videogametheme" id="2264" value="Science Fiction" />
		
									
			

			      			

			      				
		 			

			
		
					<link type="videogameseries" id="31089" value="Star Nomad" />
		
									
			

			      				
		 			

			
		
					<link type="videogamemode" id="2149" value="Single-Player" />
		
									
			

			               				<minplayers value="1" />
						               				<maxplayers value="1" />
						               				<releasedate value="2014-07-21" />
						      				
		 			

			
		
					<link type="videogamedeveloper" id="28431" value="Halfgeek Studios" />
		
									
			

			      				
		 			

			
		
					<link type="videogamepublisher" id="28431" value="Halfgeek Studios" />
		
									
			

			      			

			      			

			      			

			      			

			
	

	

	
	
	
   		<statistics page="1">
								<ratings >
			<usersrated value="0" />
			<average value="0" />
			<bayesaverage value="0" />

			<ranks>
															<rank type="subtype" id="32" name="videogame" friendlyname="Video Game Rank" value="Not Ranked" bayesaverage="Not Ranked" />
																				<rank type="family" id="4729" name="macintosh" friendlyname="Macintosh Rank" value="Not Ranked" bayesaverage="Not Ranked" />
											<rank type="family" id="4977" name="pc" friendlyname="Windows Rank" value="Not Ranked" bayesaverage="Not Ranked" />
											<rank type="family" id="6063" name="android" friendlyname="Android Rank" value="Not Ranked" bayesaverage="Not Ranked" />
											<rank type="family" id="6826" name="ipad" friendlyname="iPad Rank" value="Not Ranked" bayesaverage="Not Ranked" />
												</ranks>

			<stddev value="0" />
			<median value="0" />
			<owned value="2" />
			<trading value="0" />
			<wanting value="0" />
			<wishing value="0" />
			<numcomments value="0" />
			<numweights value="0" />
			<averageweight value="0" />
			</ratings>
								</statistics>
     
	
          
</item>
</items>