<?xml version="1.0" encoding="utf-8"?><items termsofuse="https://boardgamegeek.com/xmlapi/termsofuse"><item type="rpgitem" id="168118">
         <thumbnail>https://cf.geekdo-images.com/thumb/img/h8ceGMNwzL4IJ9b4FGgNDG7axbg=/fit-in/200x150/pic2282590.png</thumbnail>
      <image>https://cf.geekdo-images.com/original/img/rDIHzQ3Jq5qvMJHwA10S-yknalA=/0x0/pic2282590.png</image>
                                     				
				<name type="primary" sortindex="1" value="Save Game" />
			
						                           
						      				
		 			

			
		
					<link type="rpg" id="203" value="Fate Core" />
		
									
			

			               													<description>From publisher blurb:&amp;#10;&amp;#10;THE GLITCH HAS COME TO TENDORIA&amp;#10;&amp;#10;A vicious computer virus threatens to corrupt the entire internet, and the only ones standing in its way are the characters from your video games.&amp;#10;&amp;#10;8-bit heroes battle monsters and corrupted files&amp;mdash;it's Wreck-It Ralph meets Lord of the Rings in a fight for the fate of the world!&amp;#10;&amp;#10;This 56-page Fate Core adventure provides a complete world to adventure in, including randomized character generation rules, ideas to govern digital adventures, and new Fate point hacks.&amp;#10;&amp;#10;PIXELS ARE FALLING. IT&amp;rsquo;S UP TO YOU TO SAVE GAME!&amp;#10;&amp;#10;</description>
										               				<yearpublished value="2014" />
						      				
		 			

			
		
					<link type="rpggenre" id="946" value="Modern (Pop Culture)" />
		
									
				
		 			

			
		
					<link type="rpggenre" id="183" value="Science Fiction" />
		
									
			

			      			

			      				
		 			

			
		
					<link type="rpgseries" id="26090" value="A World of Adventure for Fate Core System" />
		
									
			

			               				<seriescode value="" />
						      				
		 			

			
		
					<link type="rpgcategory" id="2107" value="Campaign Setting (game world)" />
		
									
				
		 			

			
		
					<link type="rpgcategory" id="2084" value="Scenario / Adventure / Module" />
		
									
				
		 			

			
		
					<link type="rpgcategory" id="2108" value="Sourcebook (rules/options to enhance play)" />
		
									
			

			      				
		 			

			
		
					<link type="rpgmechanic" id="2680" value="Dice (Primarily Fudge/dF)" />
		
									
				
		 			

			
		
					<link type="rpgmechanic" id="2100" value="Point Based (allocate points to get skills, powers, etc)" />
		
									
				
		 			

			
		
					<link type="rpgmechanic" id="2094" value="Skill Based (buy or gain skills)" />
		
									
				
		 			

			
		
					<link type="rpgmechanic" id="2098" value="Trait / Aspect Based (personality affects gameplay)" />
		
									
			

			      				
		 			

			
		
					<link type="rpgpublisher" id="9656" value="Evil Hat Productions" />
		
									
			

			      				
		 			

			
		
					<link type="rpgdesigner" id="16824" value="Robert Wieland" />
		
									
			

			      				
		 			

			
		
					<link type="rpgartist" id="16593" value="Brian Patterson" />
		
									
			

			      				
		 			

			
		
					<link type="rpgproducer" id="13432" value="Leonard Balsera" />
		
									
				
		 			

			
		
					<link type="rpgproducer" id="13428" value="Robert Donoghue" />
		
									
				
		 			

			
		
					<link type="rpgproducer" id="13431" value="Fred Hicks" />
		
									
				
		 			

			
		
					<link type="rpgproducer" id="67958" value="Joshua Yearsley" />
		
									
			

			
	

	

	
	
	
   		<statistics page="1">
								<ratings >
			<usersrated value="7" />
			<average value="8" />
			<bayesaverage value="5.9928" />

			<ranks>
															<rank type="subtype" id="16" name="rpgitem" friendlyname="RPG Item Rank" value="3500" bayesaverage="5.9928" />
												</ranks>

			<stddev value="1.19523" />
			<median value="0" />
			<owned value="61" />
			<trading value="0" />
			<wanting value="0" />
			<wishing value="4" />
			<numcomments value="2" />
			<numweights value="0" />
			<averageweight value="0" />
			</ratings>
								</statistics>
     
	
          
</item>
</items>